jsonate/__init__.py
jsonate/apps.py
jsonate/decorators.py
jsonate/django_ver.py
jsonate/exceptions.py
jsonate/fields.py
jsonate/form_fields.py
jsonate/http.py
jsonate/json_encoder.py
jsonate/models.py
jsonate/monkey_patches.py
jsonate/utils.py
jsonate/widgets.py
jsonate/templatetags/__init__.py
jsonate/templatetags/jsonate_tags.py
jsonate-0.5.1.dist-info/METADATA
jsonate-0.5.1.dist-info/RECORD
jsonate-0.5.1.dist-info/WHEEL
jsonate-0.5.1.dist-info/top_level.txt
