Metadata-Version: 2.1
Name: jsonate
Version: 0.5.1
Summary: Django library that can make ANYTHING into json
Home-page: http://jsonate.com
Author: James Robert
Author-email: jiaaro@gmail.com
License: MIT
Keywords: django json templatetags
Platform: UNKNOWN
Classifier: Development Status :: 4 - Beta
Classifier: License :: OSI Approved :: MIT License
Classifier: Programming Language :: Python
Classifier: Framework :: Django
Classifier: Environment :: Web Environment
Classifier: Intended Audience :: Developers
Classifier: Operating System :: OS Independent
Classifier: Topic :: Internet :: WWW/HTTP
Classifier: Topic :: Utilities
Requires-Dist: django (>=1.7)
Requires-Dist: future (>=0.16.0)
